treasurbox/__init__.py
treasurbox/work_mondodb.py
treasurbox/work_mysql.py
treasurbox/work_postgresql.py
treasurbox/work_redis.py
treasurbox/work_requests.py
treasurbox/src/__init__.py
treasurbox/src/work_decorator.py
treasurbox/src/work_faker.py
treasurbox/src/work_yaml.py
treasurbox-1.0.40.dist-info/LICENSE
treasurbox-1.0.40.dist-info/METADATA
treasurbox-1.0.40.dist-info/WHEEL
treasurbox-1.0.40.dist-info/top_level.txt
treasurbox-1.0.40.dist-info/RECORD
