Metadata-Version: 2.1
Name: treasurbox
Version: 1.0.40
Summary: A small example package
Home-page: UNKNOWN
Author: Alan
Author-email: linanaicyt@163.com
License: MIT
Keywords: Mysql,Python,decorator
Platform: UNKNOWN
Classifier: Programming Language :: Python :: 3
Classifier: License :: OSI Approved :: MIT License
Classifier: Operating System :: OS Independent
Requires-Python: >=3.6
License-File: LICENSE
Requires-Dist: requests
Requires-Dist: pyyaml
Requires-Dist: pymysql
Requires-Dist: decorator
Requires-Dist: faker (>=30.8.2)
Requires-Dist: fake-useragent (>=1.5.1)
Requires-Dist: numpy (>=2.0.2)
Requires-Dist: pymongo
Requires-Dist: redis
Requires-Dist: loguru
Requires-Dist: jsonpath
